{"figuras": [{"diapositiva":1,"nombre":"Obj_1_1","tipo":"Rectángulo","colorHex":"#4472C4","bordeHex":"#2F528F","ancho_cm":33.867,"alto_cm":4.982,"posX_cm":0,"posY_cm":14.068,"ancho_px":1280,"alto_px":188,"posX_px":0,"posY_px":532,"rotacion":0},{"diapositiva":1,"nombre":"Obj_1_2","tipo":"Rectángulo","colorHex":"#ED7D31","bordeHex":"#AE5A21","ancho_cm":17.78,"alto_cm":4.982,"posX_cm":0,"posY_cm":0,"ancho_px":672,"alto_px":188,"posX_px":0,"posY_px":0,"rotacion":0},{"diapositiva":1,"nombre":"Obj_1_3","tipo":"Rectángulo","colorHex":"#70AD47","bordeHex":"#507E32","ancho_cm":16.087,"alto_cm":4.982,"posX_cm":17.78,"posY_cm":0,"ancho_px":608,"alto_px":188,"posX_px":672,"posY_px":0,"rotacion":0},{"diapositiva":1,"nombre":"Obj_1_4","tipo":"Rectángulo","colorHex":"#70AD47","bordeHex":"#507E32","ancho_cm":16.087,"alto_cm":5.666,"posX_cm":0,"posY_cm":4.982,"ancho_px":608,"alto_px":214,"posX_px":0,"posY_px":188,"rotacion":0},{"diapositiva":1,"nombre":"Obj_1_5","tipo":"Rectángulo","colorHex":"#4472C4","bordeHex":"#2F528F","ancho_cm":17.78,"alto_cm":6.912,"posX_cm":16.087,"posY_cm":4.982,"ancho_px":672,"alto_px":261,"posX_px":608,"posY_px":188,"rotacion":0},{"diapositiva":1,"nombre":"Obj_1_6","tipo":"Rectángulo","colorHex":"#FFC000","bordeHex":"#BC8C00","ancho_cm":16.087,"alto_cm":3.419,"posX_cm":0,"posY_cm":10.648,"ancho_px":608,"alto_px":129,"posX_px":0,"posY_px":402,"rotacion":0},{"diapositiva":1,"nombre":"Obj_1_7","tipo":"Rectángulo","colorHex":"#A5A5A5","bordeHex":"#787878","ancho_cm":17.78,"alto_cm":2.174,"posX_cm":16.087,"posY_cm":11.894,"ancho_px":672,"alto_px":82,"posX_px":608,"posY_px":450,"rotacion":0},{"diapositiva":1,"nombre":"Obj_1_8","tipo":"Círculo/Ovalo","colorHex":"#4472C4","bordeHex":"#2F528F","ancho_cm":2.222,"alto_cm":2.573,"posX_cm":2.893,"posY_cm":1.563,"ancho_px":84,"alto_px":97,"posX_px":109,"posY_px":59,"rotacion":0},{"diapositiva":1,"nombre":"Obj_1_9","tipo":"Círculo/Ovalo","colorHex":"#4472C4","bordeHex":"#2F528F","ancho_cm":2.222,"alto_cm":2.573,"posX_cm":2.893,"posY_cm":11.089,"ancho_px":84,"alto_px":97,"posX_px":109,"posY_px":419,"rotacion":0},{"diapositiva":1,"nombre":"Obj_1_10","tipo":"Triángulo","colorHex":"#4472C4","bordeHex":"#2F528F","ancho_cm":2.893,"alto_cm":2.68,"posX_cm":24.342,"posY_cm":1.456,"ancho_px":109,"alto_px":101,"posX_px":920,"posY_px":55,"rotacion":0},{"diapositiva":1,"nombre":"Obj_1_11","tipo":"Imagen","colorHex":"#FFFFFF","bordeHex":"","ancho_cm":4.26,"alto_cm":4.26,"posX_cm":24.335,"posY_cm":9.728,"ancho_px":161,"alto_px":161,"posX_px":920,"posY_px":368,"rotacion":0},{"diapositiva":1,"nombre":"Obj_1_12","tipo":"Triángulo","colorHex":"#4472C4","bordeHex":"#2F528F","ancho_cm":2.893,"alto_cm":2.68,"posX_cm":12.2,"posY_cm":1.151,"ancho_px":109,"alto_px":101,"posX_px":461,"posY_px":44,"rotacion":45.29848}]}
